MANIFEST.in
setup.py
tox.ini
Acolyte.egg-info/PKG-INFO
Acolyte.egg-info/SOURCES.txt
Acolyte.egg-info/dependency_links.txt
Acolyte.egg-info/entry_points.txt
Acolyte.egg-info/requires.txt
Acolyte.egg-info/top_level.txt
acolyte/__init__.py
acolyte/exception.py
acolyte/api/__init__.py
acolyte/api/app.py
acolyte/api/flow.py
acolyte/api/flow_executor.py
acolyte/api/route.py
acolyte/api/hook/__init__.py
acolyte/api/hook/github.py
acolyte/builtin_ext/__init__.py
acolyte/builtin_ext/github.py
acolyte/builtin_ext/mooncake.py
acolyte/core/__init__.py
acolyte/core/action_queue.py
acolyte/core/bootstrap.py
acolyte/core/context.py
acolyte/core/flow.py
acolyte/core/flow_executor_service.py
acolyte/core/flow_service.py
acolyte/core/job.py
acolyte/core/job_service.py
acolyte/core/message.py
acolyte/core/mgr.py
acolyte/core/notify.py
acolyte/core/notify_logic.py
acolyte/core/service.py
acolyte/core/user.py
acolyte/core/user_service.py
acolyte/core/view.py
acolyte/core/storage/__init__.py
acolyte/core/storage/flow_discard_reason.py
acolyte/core/storage/flow_instance.py
acolyte/core/storage/flow_instance_group.py
acolyte/core/storage/flow_template.py
acolyte/core/storage/job_action_data.py
acolyte/core/storage/job_instance.py
acolyte/core/storage/notify_index.py
acolyte/core/storage/role.py
acolyte/core/storage/user.py
acolyte/core/storage/user_token.py
acolyte/testing/__init__.py
acolyte/testing/mock.py
acolyte/testing/runalltests.py
acolyte/testing/builtin_ext/__init__.py
acolyte/testing/builtin_ext/github.py
acolyte/testing/builtin_ext/mock_push.py
acolyte/testing/builtin_ext/mock_travis.py
acolyte/testing/core/__init__.py
acolyte/testing/core/action_barrier.py
acolyte/testing/core/action_queue.py
acolyte/testing/core/context.py
acolyte/testing/core/flow_executor_service.py
acolyte/testing/core/flow_instance_group.py
acolyte/testing/core/flow_service.py
acolyte/testing/core/job.py
acolyte/testing/core/mgr.py
acolyte/testing/core/mgr_define.py
acolyte/testing/core/notify_logic.py
acolyte/testing/core/run_time_constraint.py
acolyte/testing/core/user_service.py
acolyte/testing/core/storage/__init__.py
acolyte/testing/core/storage/user.py
