Metadata-Version: 1.1
Name: Acolyte
Version: 0.0.1
Summary: An interactive workflow framework, you can use it to build CI, CD system
Home-page: https://github.com/easemob/acolyte
Author: ChiHongze
Author-email: chihz@easemob.com
License: MIT
Platform: UNKNOWN
Classifier: Development Status :: 3 - Alpha
Classifier: Environment :: Console
Classifier: Intended Audience :: Developers
Classifier: License :: OSI Approved :: MIT License
Classifier: Operating System :: POSIX
Classifier: Programming Language :: Python
Classifier: Programming Language :: Python :: 3.5
